config/__init__.py
config/__pycache__/__init__.cpython-312.pyc
config/asr_configuration/__init__.py
config/asr_configuration/default_asr_config.yml
config/misc/__init__.py
config/misc/sound/__init__.py
config/misc/sound/c1bccaed.wav
config/models/__init__.py
config/models/models.yml
config/patterns/__init__.py
config/patterns/end_conversation_patterns.yml
config/patterns/fallback_patterns.yml
config/personalities/__init__.py
config/personalities/conversational-user.yml
config/personalities/curious-user.yml
config/personalities/direct-user.yml
config/personalities/disorganized-user.yml
config/personalities/elderly-user.yml
config/personalities/formal-user.yml
config/personalities/impatient-user.yml
config/personalities/rude-user.yml
config/personalities/sarcastic-user.yml
config/personalities/skeptical-user.yml
config/types/__init__.py
config/types/currency.yml
config/types/phone_number.yml
data/__init__.py
data/__pycache__/__init__.cpython-312.pyc
data/audio_files/__init__.py
data/audio_files/output.mp3
data/audio_files/output.wav
data/cache/__init__.py
data/cache/image_register.json
data/cache/pdf_register.json
data/cache/webpage_register.json
data/connectors/__init__.py
data/connectors/dialogflow.yml
data/connectors/julie.yml
data/connectors/kuki.yml
data/connectors/millionbot_ada.yml
data/connectors/rasa.yml
data/connectors/serviceform.yml
data/connectors/taskyto.yml
data/element_lists/__init__.py
data/element_lists/list_of_things.yml
data/list_functions/__init__.py
data/list_functions/number_list.py
data/pdfs/Normativa_TFMs_EPS.pdf
data/pdfs/__init__.py
data/readme_data/__init__.py
data/readme_data/img.png
metamorphic/__init__.py
metamorphic/results.py
metamorphic/rule_utils.py
metamorphic/rules.py
metamorphic/tests.py
metamorphic/text_comparison_utils.py
technologies/__init__.py
technologies/chatbot_connectors.py
technologies/chatbots.py
technologies/taskyto.py
user_sim/__init__.py
user_sim/cli/__init__.py
user_sim/cli/cli.py
user_sim/cli/gen_user_profile.py
user_simulator-0.4.8.dist-info/licenses/LICENSE.txt
user_simulator-0.4.8.dist-info/METADATA
user_simulator-0.4.8.dist-info/WHEEL
user_simulator-0.4.8.dist-info/entry_points.txt
user_simulator-0.4.8.dist-info/top_level.txt
user_simulator-0.4.8.dist-info/RECORD
