Metadata-Version: 2.4
Name: user-simulator
Version: 0.4.8
Summary: LLM-based user simulator for chatbot testing.
Author: Alejandro Del Pozzo Escalera, Juan de Lara Jaramillo, Esther Guerra Sánchez
License: MIT License
Project-URL: Homepage, https://github.com/satori-chatbots/user-simulator
Requires-Python: >=3.12
License-File: LICENSE.txt
Requires-Dist: allpairspy>=2.5.1
Requires-Dist: beautifulsoup4>=4.13.4
Requires-Dist: build>=1.3.0
Requires-Dist: chatbot-connectors>=0.6.0
Requires-Dist: colorama>=0.4.6
Requires-Dist: httpx>=0.28.1
Requires-Dist: inflect>=7.0.0
Requires-Dist: langchain>=0.3.25
Requires-Dist: langchain-openai>=0.3.23
Requires-Dist: openai>=1.0.0
Requires-Dist: pandas>=2.3.0
Requires-Dist: pillow>=11.2.1
Requires-Dist: pydantic>=2.0.0
Requires-Dist: pymupdf==1.26.1
Requires-Dist: pyyaml>=6.0.2
Requires-Dist: requests>=2.32.4
Requires-Dist: scikit-learn>=1.7.0
Requires-Dist: selenium>=4.33.0
Requires-Dist: sqlalchemy==2.0.41
Requires-Dist: twine>=6.1.0
Requires-Dist: typing-extensions>=4.13.2
Requires-Dist: webdriver-manager>=4.0.2
Requires-Dist: zstandard==0.23.0
Dynamic: license-file
